{"users":[{"user_id":"d2110c1b-6cbf-459b-ad47-b0567ed1f726","deposit_accounts":[],"savings_accounts":[{"account_id":"dc4a6fbd-afbc-48e7-8a46-a56749b4203c","physical_cards":[],"virtual_cards":[],"top_up_operations":[],"purchase_operations":[],"transfer_operations":[],"cash_withdrawal_operations":[]}],"debit_card_accounts":[{"account_id":"20ddc38e-5c07-4588-b219-65423735eb9c","physical_cards":[],"virtual_cards":[],"top_up_operations":[],"purchase_operations":[],"transfer_operations":[],"cash_withdrawal_operations":[]}],"credit_card_accounts":[]},{"user_id":"2befed8c-4b09-4259-a9f3-2317f116e302","deposit_accounts":[],"savings_accounts":[{"account_id":"1a0ca92e-6157-4338-8074-2ee3a5b7230d","physical_cards":[],"virtual_cards":[],"top_up_operations":[],"purchase_operations":[],"transfer_operations":[],"cash_withdrawal_operations":[]}],"debit_card_accounts":[{"account_id":"03cc69a7-ad3c-4974-ab55-4b813ed356e3","physical_cards":[],"virtual_cards":[],"top_up_operations":[],"purchase_operations":[],"transfer_operations":[],"cash_withdrawal_operations":[]}],"credit_card_accounts":[]},{"user_id":"151d1d5a-0836-489d-b75e-d5f284ba330f","deposit_accounts":[],"savings_accounts":[{"account_id":"57330cac-8f8a-42cf-afc0-20a59569d52c","physical_cards":[],"virtual_cards":[],"top_up_operations":[],"purchase_operations":[],"transfer_operations":[],"cash_withdrawal_operations":[]}],"debit_card_accounts":[{"account_id":"1fde3972-69c8-42ee-9d52-516c16adf2e0","physical_cards":[],"virtual_cards":[],"top_up_operations":[],"purchase_operations":[],"transfer_operations":[],"cash_withdrawal_operations":[]}],"credit_card_accounts":[]},{"user_id":"974e369b-9a68-4f74-974a-0dfc48677dfd","deposit_accounts":[],"savings_accounts":[{"account_id":"e3906e74-6401-45cd-9d30-60ef761ccc7c","physical_cards":[],"virtual_cards":[],"top_up_operations":[],"purchase_operations":[],"transfer_operations":[],"cash_withdrawal_operations":[]}],"debit_card_accounts":[{"account_id":"c87fa1f5-301d-437a-b484-76e0f0ab4307","physical_cards":[],"virtual_cards":[],"top_up_operations":[],"purchase_operations":[],"transfer_operations":[],"cash_withdrawal_operations":[]}],"credit_card_accounts":[]},{"user_id":"35af6308-0c6f-4582-b028-a085841790c3","deposit_accounts":[],"savings_accounts":[{"account_id":"a4eb9203-b807-4baa-b321-bcc12ab25e29","physical_cards":[],"virtual_cards":[],"top_up_operations":[],"purchase_operations":[],"transfer_operations":[],"cash_withdrawal_operations":[]}],"debit_card_accounts":[{"account_id":"62a86836-a908-482f-965e-c367fcdc15de","physical_cards":[],"virtual_cards":[],"top_up_operations":[],"purchase_operations":[],"transfer_operations":[],"cash_withdrawal_operations":[]}],"credit_card_accounts":[]},{"user_id":"067d3075-5415-4eca-a717-cfeb02727355","deposit_accounts":[],"savings_accounts":[{"account_id":"9f553f45-d79b-4f87-8a5b-942cf008d0c1","physical_cards":[],"virtual_cards":[],"top_up_operations":[],"purchase_operations":[],"transfer_operations":[],"cash_withdrawal_operations":[]}],"debit_card_accounts":[{"account_id":"de5c0c48-d953-4b2d-bba0-f2a7189aa5e5","physical_cards":[],"virtual_cards":[],"top_up_operations":[],"purchase_operations":[],"transfer_operations":[],"cash_withdrawal_operations":[]}],"credit_card_accounts":[]},{"user_id":"27ece6b0-e5d6-4986-84d7-89a1fa9b67ca","deposit_accounts":[],"savings_accounts":[{"account_id":"9623e79d-a648-4c48-a95d-fee9dc2ba369","physical_cards":[],"virtual_cards":[],"top_up_operations":[],"purchase_operations":[],"transfer_operations":[],"cash_withdrawal_operations":[]}],"debit_card_accounts":[{"account_id":"7abfcda2-a9d2-415e-8067-3e1cba49e553","physical_cards":[],"virtual_cards":[],"top_up_operations":[],"purchase_operations":[],"transfer_operations":[],"cash_withdrawal_operations":[]}],"credit_card_accounts":[]},{"user_id":"67ee9db5-1815-4d02-8da5-dfff76c235e0","deposit_accounts":[],"savings_accounts":[{"account_id":"7f7c1909-69d0-430d-b4ce-cfd80f54591f","physical_cards":[],"virtual_cards":[],"top_up_operations":[],"purchase_operations":[],"transfer_operations":[],"cash_withdrawal_operations":[]}],"debit_card_accounts":[{"account_id":"3fa00a82-af32-4cdf-8fcf-9b45a0f1c148","physical_cards":[],"virtual_cards":[],"top_up_operations":[],"purchase_operations":[],"transfer_operations":[],"cash_withdrawal_operations":[]}],"credit_card_accounts":[]},{"user_id":"ee52d533-6380-426a-b10d-61c82eed67cd","deposit_accounts":[],"savings_accounts":[{"account_id":"c69f38d8-230e-4a30-8f99-3a9ba80b989f","physical_cards":[],"virtual_cards":[],"top_up_operations":[],"purchase_operations":[],"transfer_operations":[],"cash_withdrawal_operations":[]}],"debit_card_accounts":[{"account_id":"5b60e3b4-6923-4baa-8ca9-eee3e687e729","physical_cards":[],"virtual_cards":[],"top_up_operations":[],"purchase_operations":[],"transfer_operations":[],"cash_withdrawal_operations":[]}],"credit_card_accounts":[]},{"user_id":"ae653648-5780-484c-95e1-3693272626a6","deposit_accounts":[],"savings_accounts":[{"account_id":"470bddc2-b407-4bf7-a09f-f8c7fadbf5bc","physical_cards":[],"virtual_cards":[],"top_up_operations":[],"purchase_operations":[],"transfer_operations":[],"cash_withdrawal_operations":[]}],"debit_card_accounts":[{"account_id":"3fa3ca3c-2f6c-4cc3-8e28-375a7b39bab8","physical_cards":[],"virtual_cards":[],"top_up_operations":[],"purchase_operations":[],"transfer_operations":[],"cash_withdrawal_operations":[]}],"credit_card_accounts":[]},{"user_id":"68316615-1d65-4675-b9f8-e8b8df32f44b","deposit_accounts":[],"savings_accounts":[{"account_id":"00dded76-8663-4c24-a5b8-6027a8717804","physical_cards":[],"virtual_cards":[],"top_up_operations":[],"purchase_operations":[],"transfer_operations":[],"cash_withdrawal_operations":[]}],"debit_card_accounts":[{"account_id":"1387372b-5f1b-404a-9323-5f0ce7ca1a1c","physical_cards":[],"virtual_cards":[],"top_up_operations":[],"purchase_operations":[],"transfer_operations":[],"cash_withdrawal_operations":[]}],"credit_card_accounts":[]},{"user_id":"89508c4b-af5b-4ad3-94a2-3775da086aeb","deposit_accounts":[],"savings_accounts":[{"account_id":"6c79ff28-7cfb-49d2-87d5-1b92e6fd3ed6","physical_cards":[],"virtual_cards":[],"top_up_operations":[],"purchase_operations":[],"transfer_operations":[],"cash_withdrawal_operations":[]}],"debit_card_accounts":[{"account_id":"4b5667fd-f2f9-4323-8c84-6167b20bf0a4","physical_cards":[],"virtual_cards":[],"top_up_operations":[],"purchase_operations":[],"transfer_operations":[],"cash_withdrawal_operations":[]}],"credit_card_accounts":[]},{"user_id":"86c04f93-65bc-43cf-9f27-714413718aca","deposit_accounts":[],"savings_accounts":[{"account_id":"1ee3f71d-9a95-4c94-9735-eb8525f89d73","physical_cards":[],"virtual_cards":[],"top_up_operations":[],"purchase_operations":[],"transfer_operations":[],"cash_withdrawal_operations":[]}],"debit_card_accounts":[{"account_id":"e36399a0-9d5f-44b0-bba3-eb454a482982","physical_cards":[],"virtual_cards":[],"top_up_operations":[],"purchase_operations":[],"transfer_operations":[],"cash_withdrawal_operations":[]}],"credit_card_accounts":[]},{"user_id":"b84346af-183d-4a31-bece-53054573aac3","deposit_accounts":[],"savings_accounts":[{"account_id":"76873907-2d27-4235-bd8a-5091a44f1468","physical_cards":[],"virtual_cards":[],"top_up_operations":[],"purchase_operations":[],"transfer_operations":[],"cash_withdrawal_operations":[]}],"debit_card_accounts":[{"account_id":"b86f7c6d-040d-4ddf-8faa-dcec911a9982","physical_cards":[],"virtual_cards":[],"top_up_operations":[],"purchase_operations":[],"transfer_operations":[],"cash_withdrawal_operations":[]}],"credit_card_accounts":[]},{"user_id":"88c396cc-8f6c-41bb-9f65-6ec94b3203a4","deposit_accounts":[],"savings_accounts":[{"account_id":"3bf413fb-c54d-4726-ab25-a47d059c5a5f","physical_cards":[],"virtual_cards":[],"top_up_operations":[],"purchase_operations":[],"transfer_operations":[],"cash_withdrawal_operations":[]}],"debit_card_accounts":[{"account_id":"35895741-c35a-44e6-8427-cd1a8704db78","physical_cards":[],"virtual_cards":[],"top_up_operations":[],"purchase_operations":[],"transfer_operations":[],"cash_withdrawal_operations":[]}],"credit_card_accounts":[]},{"user_id":"332dbf8f-b8d9-4aab-8380-61c64df3edcb","deposit_accounts":[],"savings_accounts":[{"account_id":"26065b2f-74ae-4186-a182-1f5c7571ce6c","physical_cards":[],"virtual_cards":[],"top_up_operations":[],"purchase_operations":[],"transfer_operations":[],"cash_withdrawal_operations":[]}],"debit_card_accounts":[{"account_id":"41d638b5-4f54-41de-9343-25c47a042e8e","physical_cards":[],"virtual_cards":[],"top_up_operations":[],"purchase_operations":[],"transfer_operations":[],"cash_withdrawal_operations":[]}],"credit_card_accounts":[]},{"user_id":"4c9f5fbd-fa51-4f2f-bfd9-82876bb79b37","deposit_accounts":[],"savings_accounts":[{"account_id":"69650a08-4401-4a5c-985f-f23ad90291df","physical_cards":[],"virtual_cards":[],"top_up_operations":[],"purchase_operations":[],"transfer_operations":[],"cash_withdrawal_operations":[]}],"debit_card_accounts":[{"account_id":"7e642b34-88dc-4ae8-a6d0-b89373af9dab","physical_cards":[],"virtual_cards":[],"top_up_operations":[],"purchase_operations":[],"transfer_operations":[],"cash_withdrawal_operations":[]}],"credit_card_accounts":[]},{"user_id":"2c521f78-6710-47b9-b7cb-39751ef2a535","deposit_accounts":[],"savings_accounts":[{"account_id":"79dcab05-be6f-4b59-8e95-cfc5a174562d","physical_cards":[],"virtual_cards":[],"top_up_operations":[],"purchase_operations":[],"transfer_operations":[],"cash_withdrawal_operations":[]}],"debit_card_accounts":[{"account_id":"bb9c6c21-8a39-4b41-8ad5-7cc13884590d","physical_cards":[],"virtual_cards":[],"top_up_operations":[],"purchase_operations":[],"transfer_operations":[],"cash_withdrawal_operations":[]}],"credit_card_accounts":[]},{"user_id":"a6150261-da74-4dca-a46e-364ed5fd8e80","deposit_accounts":[],"savings_accounts":[{"account_id":"83253d61-92b4-45fb-a7a6-b8e1d29293d6","physical_cards":[],"virtual_cards":[],"top_up_operations":[],"purchase_operations":[],"transfer_operations":[],"cash_withdrawal_operations":[]}],"debit_card_accounts":[{"account_id":"7d3f1e72-8c56-42ba-bd37-96ab4d4d8fdb","physical_cards":[],"virtual_cards":[],"top_up_operations":[],"purchase_operations":[],"transfer_operations":[],"cash_withdrawal_operations":[]}],"credit_card_accounts":[]},{"user_id":"5719b7ad-010e-41ef-8127-44abdaac3422","deposit_accounts":[],"savings_accounts":[{"account_id":"b7e521b8-63d6-460a-8806-f6e21d67b5b6","physical_cards":[],"virtual_cards":[],"top_up_operations":[],"purchase_operations":[],"transfer_operations":[],"cash_withdrawal_operations":[]}],"debit_card_accounts":[{"account_id":"d860a618-3a44-4b42-aaf9-6299e402df6c","physical_cards":[],"virtual_cards":[],"top_up_operations":[],"purchase_operations":[],"transfer_operations":[],"cash_withdrawal_operations":[]}],"credit_card_accounts":[]},{"user_id":"30433e0d-a0bf-4d37-938b-481050539994","deposit_accounts":[],"savings_accounts":[{"account_id":"9def66bf-c2b1-4977-a34b-8cb1dde27656","physical_cards":[],"virtual_cards":[],"top_up_operations":[],"purchase_operations":[],"transfer_operations":[],"cash_withdrawal_operations":[]}],"debit_card_accounts":[{"account_id":"c8e9c252-b4ed-47ca-953e-215b241d4ea6","physical_cards":[],"virtual_cards":[],"top_up_operations":[],"purchase_operations":[],"transfer_operations":[],"cash_withdrawal_operations":[]}],"credit_card_accounts":[]},{"user_id":"5abf9b3d-73d1-4793-89a8-63c0027b3e4f","deposit_accounts":[],"savings_accounts":[{"account_id":"8d7a70f5-fe7f-455d-8458-80797228e080","physical_cards":[],"virtual_cards":[],"top_up_operations":[],"purchase_operations":[],"transfer_operations":[],"cash_withdrawal_operations":[]}],"debit_card_accounts":[{"account_id":"22857605-6815-4bc6-8ad8-791a22c53544","physical_cards":[],"virtual_cards":[],"top_up_operations":[],"purchase_operations":[],"transfer_operations":[],"cash_withdrawal_operations":[]}],"credit_card_accounts":[]},{"user_id":"9416695b-5340-4034-92f2-0156c444aa1f","deposit_accounts":[],"savings_accounts":[{"account_id":"6d22ad1d-14c1-429e-aa28-6f009eff0be9","physical_cards":[],"virtual_cards":[],"top_up_operations":[],"purchase_operations":[],"transfer_operations":[],"cash_withdrawal_operations":[]}],"debit_card_accounts":[{"account_id":"2a66274f-bddd-4fbd-8ef0-5f229b3e13be","physical_cards":[],"virtual_cards":[],"top_up_operations":[],"purchase_operations":[],"transfer_operations":[],"cash_withdrawal_operations":[]}],"credit_card_accounts":[]},{"user_id":"ec826002-0af1-4405-92b0-b120a4d78382","deposit_accounts":[],"savings_accounts":[{"account_id":"3ef01c96-f628-45b9-80a0-1ac6726b8532","physical_cards":[],"virtual_cards":[],"top_up_operations":[],"purchase_operations":[],"transfer_operations":[],"cash_withdrawal_operations":[]}],"debit_card_accounts":[{"account_id":"03efa675-0de1-4b8f-b6b9-ecf1b4cd01b3","physical_cards":[],"virtual_cards":[],"top_up_operations":[],"purchase_operations":[],"transfer_operations":[],"cash_withdrawal_operations":[]}],"credit_card_accounts":[]},{"user_id":"6d4caa9c-4051-4ef7-94fc-199165fa6192","deposit_accounts":[],"savings_accounts":[{"account_id":"9b3812b8-d14c-4ddc-86ef-4bd29ae5fe8e","physical_cards":[],"virtual_cards":[],"top_up_operations":[],"purchase_operations":[],"transfer_operations":[],"cash_withdrawal_operations":[]}],"debit_card_accounts":[{"account_id":"fd606e52-3eee-4a9a-b053-44ab397c68b6","physical_cards":[],"virtual_cards":[],"top_up_operations":[],"purchase_operations":[],"transfer_operations":[],"cash_withdrawal_operations":[]}],"credit_card_accounts":[]},{"user_id":"87c6854a-8608-4459-b9c6-54124d03e9c8","deposit_accounts":[],"savings_accounts":[{"account_id":"c3a96448-ba01-4e88-a1a8-fe371428c1b8","physical_cards":[],"virtual_cards":[],"top_up_operations":[],"purchase_operations":[],"transfer_operations":[],"cash_withdrawal_operations":[]}],"debit_card_accounts":[{"account_id":"e1dc11dc-0439-49c0-9ef0-55b8538a249c","physical_cards":[],"virtual_cards":[],"top_up_operations":[],"purchase_operations":[],"transfer_operations":[],"cash_withdrawal_operations":[]}],"credit_card_accounts":[]},{"user_id":"981fdc9b-8c5f-4a34-be6f-c309dae5f61c","deposit_accounts":[],"savings_accounts":[{"account_id":"a05743c3-d798-40fe-b728-7e0d2e543980","physical_cards":[],"virtual_cards":[],"top_up_operations":[],"purchase_operations":[],"transfer_operations":[],"cash_withdrawal_operations":[]}],"debit_card_accounts":[{"account_id":"b6944b72-f2dd-4974-a700-21b6b7c47071","physical_cards":[],"virtual_cards":[],"top_up_operations":[],"purchase_operations":[],"transfer_operations":[],"cash_withdrawal_operations":[]}],"credit_card_accounts":[]},{"user_id":"d76aba4d-772b-48b3-bbc9-3219400fe0c8","deposit_accounts":[],"savings_accounts":[{"account_id":"e839cb80-64db-4efd-8e70-9c3271aa3894","physical_cards":[],"virtual_cards":[],"top_up_operations":[],"purchase_operations":[],"transfer_operations":[],"cash_withdrawal_operations":[]}],"debit_card_accounts":[{"account_id":"b92f6108-0d27-4a59-874b-b3574750662b","physical_cards":[],"virtual_cards":[],"top_up_operations":[],"purchase_operations":[],"transfer_operations":[],"cash_withdrawal_operations":[]}],"credit_card_accounts":[]},{"user_id":"31b6f4b1-8000-4bd0-9829-f9a6a0a6fa58","deposit_accounts":[],"savings_accounts":[{"account_id":"a41b8ebd-048b-44a6-bab6-89a0e0a06227","physical_cards":[],"virtual_cards":[],"top_up_operations":[],"purchase_operations":[],"transfer_operations":[],"cash_withdrawal_operations":[]}],"debit_card_accounts":[{"account_id":"347aab7f-b68f-4925-a5ca-275bd71f4266","physical_cards":[],"virtual_cards":[],"top_up_operations":[],"purchase_operations":[],"transfer_operations":[],"cash_withdrawal_operations":[]}],"credit_card_accounts":[]},{"user_id":"28824359-9a20-4681-95ba-f1d05c5e246e","deposit_accounts":[],"savings_accounts":[{"account_id":"43959fc8-ac78-4489-82c8-d59b8aa32917","physical_cards":[],"virtual_cards":[],"top_up_operations":[],"purchase_operations":[],"transfer_operations":[],"cash_withdrawal_operations":[]}],"debit_card_accounts":[{"account_id":"8486160a-a877-4428-9bec-2cf64850789f","physical_cards":[],"virtual_cards":[],"top_up_operations":[],"purchase_operations":[],"transfer_operations":[],"cash_withdrawal_operations":[]}],"credit_card_accounts":[]},{"user_id":"8f393486-861c-4bc0-84b3-d75c28be6550","deposit_accounts":[],"savings_accounts":[{"account_id":"ede69bf3-9462-4ccd-be65-66d44727dfcd","physical_cards":[],"virtual_cards":[],"top_up_operations":[],"purchase_operations":[],"transfer_operations":[],"cash_withdrawal_operations":[]}],"debit_card_accounts":[{"account_id":"13bedf4e-3b25-4f3a-a3b2-dc422cadaafe","physical_cards":[],"virtual_cards":[],"top_up_operations":[],"purchase_operations":[],"transfer_operations":[],"cash_withdrawal_operations":[]}],"credit_card_accounts":[]},{"user_id":"ca181710-54fc-427d-8b9c-fb65824a38ee","deposit_accounts":[],"savings_accounts":[{"account_id":"552b189e-c9bb-43a4-b678-59b0da565547","physical_cards":[],"virtual_cards":[],"top_up_operations":[],"purchase_operations":[],"transfer_operations":[],"cash_withdrawal_operations":[]}],"debit_card_accounts":[{"account_id":"acde9906-a6ac-4f42-b87d-20621caecca1","physical_cards":[],"virtual_cards":[],"top_up_operations":[],"purchase_operations":[],"transfer_operations":[],"cash_withdrawal_operations":[]}],"credit_card_accounts":[]},{"user_id":"87df012f-d6a6-44b6-8b98-bd5ce34fdbf1","deposit_accounts":[],"savings_accounts":[{"account_id":"aaf655cb-b20f-4c6e-a6e0-b47d811846c3","physical_cards":[],"virtual_cards":[],"top_up_operations":[],"purchase_operations":[],"transfer_operations":[],"cash_withdrawal_operations":[]}],"debit_card_accounts":[{"account_id":"20b84a72-f942-403a-bcec-49b2d41ab273","physical_cards":[],"virtual_cards":[],"top_up_operations":[],"purchase_operations":[],"transfer_operations":[],"cash_withdrawal_operations":[]}],"credit_card_accounts":[]},{"user_id":"f9f45ef1-cb8b-4ef9-a14f-9acec81057ed","deposit_accounts":[],"savings_accounts":[{"account_id":"19a7015b-1ed9-450b-94bd-9a845f29cf99","physical_cards":[],"virtual_cards":[],"top_up_operations":[],"purchase_operations":[],"transfer_operations":[],"cash_withdrawal_operations":[]}],"debit_card_accounts":[{"account_id":"375970c0-c733-45cd-81b9-bc9551946c02","physical_cards":[],"virtual_cards":[],"top_up_operations":[],"purchase_operations":[],"transfer_operations":[],"cash_withdrawal_operations":[]}],"credit_card_accounts":[]},{"user_id":"0b986568-1e91-4247-b65d-62a81caf4e71","deposit_accounts":[],"savings_accounts":[{"account_id":"dd3393c4-ed8e-48d4-ae53-8871a531f25c","physical_cards":[],"virtual_cards":[],"top_up_operations":[],"purchase_operations":[],"transfer_operations":[],"cash_withdrawal_operations":[]}],"debit_card_accounts":[{"account_id":"ca68411a-31f4-4650-bdd1-94f4446f29a8","physical_cards":[],"virtual_cards":[],"top_up_operations":[],"purchase_operations":[],"transfer_operations":[],"cash_withdrawal_operations":[]}],"credit_card_accounts":[]},{"user_id":"bfdc77cb-c664-426a-947c-4188096d23ff","deposit_accounts":[],"savings_accounts":[{"account_id":"c36fb996-e125-4324-a4be-fa7e4aa87df9","physical_cards":[],"virtual_cards":[],"top_up_operations":[],"purchase_operations":[],"transfer_operations":[],"cash_withdrawal_operations":[]}],"debit_card_accounts":[{"account_id":"afd271d4-9295-45f2-b41b-70c5ab4745d1","physical_cards":[],"virtual_cards":[],"top_up_operations":[],"purchase_operations":[],"transfer_operations":[],"cash_withdrawal_operations":[]}],"credit_card_accounts":[]},{"user_id":"0259f79a-ba01-4fb7-9f71-f67f5ff9b2b8","deposit_accounts":[],"savings_accounts":[{"account_id":"88f69582-c00d-4e1e-bfb2-c3c8a4f2c069","physical_cards":[],"virtual_cards":[],"top_up_operations":[],"purchase_operations":[],"transfer_operations":[],"cash_withdrawal_operations":[]}],"debit_card_accounts":[{"account_id":"44d28aa9-8a2c-47d4-a23a-e67c41a5a3e1","physical_cards":[],"virtual_cards":[],"top_up_operations":[],"purchase_operations":[],"transfer_operations":[],"cash_withdrawal_operations":[]}],"credit_card_accounts":[]},{"user_id":"135e5833-81b4-4f34-9283-665965214b98","deposit_accounts":[],"savings_accounts":[{"account_id":"cc82a91d-9b67-4b4c-97d0-acbe58fc2dbc","physical_cards":[],"virtual_cards":[],"top_up_operations":[],"purchase_operations":[],"transfer_operations":[],"cash_withdrawal_operations":[]}],"debit_card_accounts":[{"account_id":"2ea39ce8-e1f3-4864-aa32-295d5a8f976a","physical_cards":[],"virtual_cards":[],"top_up_operations":[],"purchase_operations":[],"transfer_operations":[],"cash_withdrawal_operations":[]}],"credit_card_accounts":[]},{"user_id":"fdd007c3-53ff-41d4-9e94-f9cb2cbe0791","deposit_accounts":[],"savings_accounts":[{"account_id":"f6798517-f16b-4f2d-9d25-3255c74587c3","physical_cards":[],"virtual_cards":[],"top_up_operations":[],"purchase_operations":[],"transfer_operations":[],"cash_withdrawal_operations":[]}],"debit_card_accounts":[{"account_id":"8bbc9e5d-ec5b-40a9-9c09-919a4e465897","physical_cards":[],"virtual_cards":[],"top_up_operations":[],"purchase_operations":[],"transfer_operations":[],"cash_withdrawal_operations":[]}],"credit_card_accounts":[]},{"user_id":"1e6b9ff1-9d89-449e-a13d-eeecd434afad","deposit_accounts":[],"savings_accounts":[{"account_id":"546d334a-831d-4077-a787-4a9f324412ca","physical_cards":[],"virtual_cards":[],"top_up_operations":[],"purchase_operations":[],"transfer_operations":[],"cash_withdrawal_operations":[]}],"debit_card_accounts":[{"account_id":"ad1c1601-fbb3-419a-8b2f-0040c470ba3c","physical_cards":[],"virtual_cards":[],"top_up_operations":[],"purchase_operations":[],"transfer_operations":[],"cash_withdrawal_operations":[]}],"credit_card_accounts":[]},{"user_id":"8236855a-3bf0-4c0d-a4f2-a421703f22f8","deposit_accounts":[],"savings_accounts":[{"account_id":"41bcf155-a7b3-4f82-b22d-8d1c17a6fce0","physical_cards":[],"virtual_cards":[],"top_up_operations":[],"purchase_operations":[],"transfer_operations":[],"cash_withdrawal_operations":[]}],"debit_card_accounts":[{"account_id":"8b7c1992-1808-4152-8658-201af6a30912","physical_cards":[],"virtual_cards":[],"top_up_operations":[],"purchase_operations":[],"transfer_operations":[],"cash_withdrawal_operations":[]}],"credit_card_accounts":[]},{"user_id":"339a69eb-22b4-4dae-b1ce-015a4326e74c","deposit_accounts":[],"savings_accounts":[{"account_id":"767a91bf-b7c2-465f-ab73-9cfc28bde4cb","physical_cards":[],"virtual_cards":[],"top_up_operations":[],"purchase_operations":[],"transfer_operations":[],"cash_withdrawal_operations":[]}],"debit_card_accounts":[{"account_id":"7a714835-a79f-4abd-996c-f3a9f2cc9c22","physical_cards":[],"virtual_cards":[],"top_up_operations":[],"purchase_operations":[],"transfer_operations":[],"cash_withdrawal_operations":[]}],"credit_card_accounts":[]},{"user_id":"d61df7cf-93ac-4a08-aa68-8369d06235a2","deposit_accounts":[],"savings_accounts":[{"account_id":"115522c4-2576-4811-b2d6-de6d015cc80c","physical_cards":[],"virtual_cards":[],"top_up_operations":[],"purchase_operations":[],"transfer_operations":[],"cash_withdrawal_operations":[]}],"debit_card_accounts":[{"account_id":"053d8ff6-056a-4e5b-b2f4-2ff802f59d54","physical_cards":[],"virtual_cards":[],"top_up_operations":[],"purchase_operations":[],"transfer_operations":[],"cash_withdrawal_operations":[]}],"credit_card_accounts":[]},{"user_id":"79ebb207-c2f2-4d05-b508-16a83b64fa12","deposit_accounts":[],"savings_accounts":[{"account_id":"4fd614c8-3061-40d6-b777-e1daaf86b4e0","physical_cards":[],"virtual_cards":[],"top_up_operations":[],"purchase_operations":[],"transfer_operations":[],"cash_withdrawal_operations":[]}],"debit_card_accounts":[{"account_id":"0ca8b1da-6dd5-4c78-93d5-f5d7207253d1","physical_cards":[],"virtual_cards":[],"top_up_operations":[],"purchase_operations":[],"transfer_operations":[],"cash_withdrawal_operations":[]}],"credit_card_accounts":[]},{"user_id":"517a1cae-df4f-43e4-b7f6-82fcde846a9d","deposit_accounts":[],"savings_accounts":[{"account_id":"1506de25-671f-48f0-a29a-498cca0d803b","physical_cards":[],"virtual_cards":[],"top_up_operations":[],"purchase_operations":[],"transfer_operations":[],"cash_withdrawal_operations":[]}],"debit_card_accounts":[{"account_id":"ace19817-6dc3-4f96-bed0-40d98fe3a3ab","physical_cards":[],"virtual_cards":[],"top_up_operations":[],"purchase_operations":[],"transfer_operations":[],"cash_withdrawal_operations":[]}],"credit_card_accounts":[]},{"user_id":"922b7dbb-6280-4231-8beb-64f2383b35e4","deposit_accounts":[],"savings_accounts":[{"account_id":"af82903a-43f9-4829-9881-d4189e64628e","physical_cards":[],"virtual_cards":[],"top_up_operations":[],"purchase_operations":[],"transfer_operations":[],"cash_withdrawal_operations":[]}],"debit_card_accounts":[{"account_id":"4faf2214-3ddc-4e4a-ae02-d2726c13cad5","physical_cards":[],"virtual_cards":[],"top_up_operations":[],"purchase_operations":[],"transfer_operations":[],"cash_withdrawal_operations":[]}],"credit_card_accounts":[]},{"user_id":"de93a9c6-a534-49e6-b598-9585f0745683","deposit_accounts":[],"savings_accounts":[{"account_id":"159c8a3d-bc22-4e24-a34a-135b89131af1","physical_cards":[],"virtual_cards":[],"top_up_operations":[],"purchase_operations":[],"transfer_operations":[],"cash_withdrawal_operations":[]}],"debit_card_accounts":[{"account_id":"9a2f7877-4abc-48b9-a6ef-56cb5ab83683","physical_cards":[],"virtual_cards":[],"top_up_operations":[],"purchase_operations":[],"transfer_operations":[],"cash_withdrawal_operations":[]}],"credit_card_accounts":[]},{"user_id":"3334cbec-429b-4db3-83f3-81c805b0e5d4","deposit_accounts":[],"savings_accounts":[{"account_id":"08ec8b7a-1a9a-4dd3-bf3a-5ccb0438166f","physical_cards":[],"virtual_cards":[],"top_up_operations":[],"purchase_operations":[],"transfer_operations":[],"cash_withdrawal_operations":[]}],"debit_card_accounts":[{"account_id":"53b26e42-4aa3-45c5-93c5-3d71e82be6c4","physical_cards":[],"virtual_cards":[],"top_up_operations":[],"purchase_operations":[],"transfer_operations":[],"cash_withdrawal_operations":[]}],"credit_card_accounts":[]},{"user_id":"6de59d82-8409-49da-9753-ddbaeabc97f3","deposit_accounts":[],"savings_accounts":[{"account_id":"e48745c3-e001-4ebf-86a7-b3d70b16c0a5","physical_cards":[],"virtual_cards":[],"top_up_operations":[],"purchase_operations":[],"transfer_operations":[],"cash_withdrawal_operations":[]}],"debit_card_accounts":[{"account_id":"71310278-e5e3-4687-a38f-011fc86e99e2","physical_cards":[],"virtual_cards":[],"top_up_operations":[],"purchase_operations":[],"transfer_operations":[],"cash_withdrawal_operations":[]}],"credit_card_accounts":[]},{"user_id":"3aadd5c0-1664-4852-a881-e68f7743e320","deposit_accounts":[],"savings_accounts":[{"account_id":"17649c7c-f06c-4a1c-aaa9-f05e2ee2b81e","physical_cards":[],"virtual_cards":[],"top_up_operations":[],"purchase_operations":[],"transfer_operations":[],"cash_withdrawal_operations":[]}],"debit_card_accounts":[{"account_id":"44f015c2-fedc-4dd7-a637-6244a42df742","physical_cards":[],"virtual_cards":[],"top_up_operations":[],"purchase_operations":[],"transfer_operations":[],"cash_withdrawal_operations":[]}],"credit_card_accounts":[]},{"user_id":"7f0ffb1a-6f28-43dc-977d-e8236b9ed3e9","deposit_accounts":[],"savings_accounts":[{"account_id":"bb364342-0411-490a-98f6-472cff214b26","physical_cards":[],"virtual_cards":[],"top_up_operations":[],"purchase_operations":[],"transfer_operations":[],"cash_withdrawal_operations":[]}],"debit_card_accounts":[{"account_id":"905c2ab0-f512-400d-8972-6c04c5d6b729","physical_cards":[],"virtual_cards":[],"top_up_operations":[],"purchase_operations":[],"transfer_operations":[],"cash_withdrawal_operations":[]}],"credit_card_accounts":[]},{"user_id":"e344059f-8f82-4c43-a732-b1afa1123887","deposit_accounts":[],"savings_accounts":[{"account_id":"2cd33917-860c-49bd-861f-11b619ec0fed","physical_cards":[],"virtual_cards":[],"top_up_operations":[],"purchase_operations":[],"transfer_operations":[],"cash_withdrawal_operations":[]}],"debit_card_accounts":[{"account_id":"c20e3187-75ce-4dde-bb3c-3a2efda1f09c","physical_cards":[],"virtual_cards":[],"top_up_operations":[],"purchase_operations":[],"transfer_operations":[],"cash_withdrawal_operations":[]}],"credit_card_accounts":[]},{"user_id":"b5623fc4-75b4-4c7c-922b-e8f5cb9f5ccc","deposit_accounts":[],"savings_accounts":[{"account_id":"4d20bf3a-51d8-4b6d-88c8-9a11fe445ec0","physical_cards":[],"virtual_cards":[],"top_up_operations":[],"purchase_operations":[],"transfer_operations":[],"cash_withdrawal_operations":[]}],"debit_card_accounts":[{"account_id":"8366eb1f-2fdf-4eba-8ea2-9bf894cb867e","physical_cards":[],"virtual_cards":[],"top_up_operations":[],"purchase_operations":[],"transfer_operations":[],"cash_withdrawal_operations":[]}],"credit_card_accounts":[]},{"user_id":"edd579b1-e189-4262-8c72-23a0b01c30e7","deposit_accounts":[],"savings_accounts":[{"account_id":"8e727b3f-348d-4805-9b84-d213168be525","physical_cards":[],"virtual_cards":[],"top_up_operations":[],"purchase_operations":[],"transfer_operations":[],"cash_withdrawal_operations":[]}],"debit_card_accounts":[{"account_id":"1cc84247-f23e-4be3-802b-0f41bf8e95fa","physical_cards":[],"virtual_cards":[],"top_up_operations":[],"purchase_operations":[],"transfer_operations":[],"cash_withdrawal_operations":[]}],"credit_card_accounts":[]},{"user_id":"40e281c3-f549-4bc1-9470-0ad9204e5b43","deposit_accounts":[],"savings_accounts":[{"account_id":"32f35a82-cc78-4f71-845c-325c2ad389f6","physical_cards":[],"virtual_cards":[],"top_up_operations":[],"purchase_operations":[],"transfer_operations":[],"cash_withdrawal_operations":[]}],"debit_card_accounts":[{"account_id":"f3c7d8dd-433f-4c93-b342-bf1e99637ef2","physical_cards":[],"virtual_cards":[],"top_up_operations":[],"purchase_operations":[],"transfer_operations":[],"cash_withdrawal_operations":[]}],"credit_card_accounts":[]},{"user_id":"304d9762-ddb7-49aa-9056-e8f9cb48e875","deposit_accounts":[],"savings_accounts":[{"account_id":"8cbe0205-033e-4f69-b2f4-64240899e8bc","physical_cards":[],"virtual_cards":[],"top_up_operations":[],"purchase_operations":[],"transfer_operations":[],"cash_withdrawal_operations":[]}],"debit_card_accounts":[{"account_id":"1e09be8b-b338-475e-b82b-220c8cf7c3b7","physical_cards":[],"virtual_cards":[],"top_up_operations":[],"purchase_operations":[],"transfer_operations":[],"cash_withdrawal_operations":[]}],"credit_card_accounts":[]},{"user_id":"76d4f8c3-b481-4c16-8350-daaa1bf8f620","deposit_accounts":[],"savings_accounts":[{"account_id":"1b501270-70d6-4ef1-9a9e-66e76398f37f","physical_cards":[],"virtual_cards":[],"top_up_operations":[],"purchase_operations":[],"transfer_operations":[],"cash_withdrawal_operations":[]}],"debit_card_accounts":[{"account_id":"5e90768e-d517-4705-a95f-f9a3a38a2c09","physical_cards":[],"virtual_cards":[],"top_up_operations":[],"purchase_operations":[],"transfer_operations":[],"cash_withdrawal_operations":[]}],"credit_card_accounts":[]},{"user_id":"ed21ada5-357b-4c4e-a4e9-8eaf5bb25490","deposit_accounts":[],"savings_accounts":[{"account_id":"c8b90f6c-e611-4620-8738-2c41965dfa7a","physical_cards":[],"virtual_cards":[],"top_up_operations":[],"purchase_operations":[],"transfer_operations":[],"cash_withdrawal_operations":[]}],"debit_card_accounts":[{"account_id":"5a1d6a63-2970-4255-9419-70f70f2f09ac","physical_cards":[],"virtual_cards":[],"top_up_operations":[],"purchase_operations":[],"transfer_operations":[],"cash_withdrawal_operations":[]}],"credit_card_accounts":[]},{"user_id":"73bd8469-3201-4234-bf56-b0bbc1d3541c","deposit_accounts":[],"savings_accounts":[{"account_id":"0a63fbcc-61d9-43a3-81d3-541e99cdb129","physical_cards":[],"virtual_cards":[],"top_up_operations":[],"purchase_operations":[],"transfer_operations":[],"cash_withdrawal_operations":[]}],"debit_card_accounts":[{"account_id":"237b2582-e4d8-4420-b26e-6b8bdd0616be","physical_cards":[],"virtual_cards":[],"top_up_operations":[],"purchase_operations":[],"transfer_operations":[],"cash_withdrawal_operations":[]}],"credit_card_accounts":[]},{"user_id":"41878d18-79e5-4119-8b55-e63234313b3f","deposit_accounts":[],"savings_accounts":[{"account_id":"ece3003e-3e66-43a9-b8f4-483d5e549e44","physical_cards":[],"virtual_cards":[],"top_up_operations":[],"purchase_operations":[],"transfer_operations":[],"cash_withdrawal_operations":[]}],"debit_card_accounts":[{"account_id":"6cdf9322-7085-44e1-9d92-1f1b258add03","physical_cards":[],"virtual_cards":[],"top_up_operations":[],"purchase_operations":[],"transfer_operations":[],"cash_withdrawal_operations":[]}],"credit_card_accounts":[]},{"user_id":"d8e9dfa1-99c1-42b5-9e92-e314341cbf8a","deposit_accounts":[],"savings_accounts":[{"account_id":"0ac6a712-92a7-401f-b84f-d787f0875043","physical_cards":[],"virtual_cards":[],"top_up_operations":[],"purchase_operations":[],"transfer_operations":[],"cash_withdrawal_operations":[]}],"debit_card_accounts":[{"account_id":"a57566d8-54a3-4f59-b084-23ac749d58c1","physical_cards":[],"virtual_cards":[],"top_up_operations":[],"purchase_operations":[],"transfer_operations":[],"cash_withdrawal_operations":[]}],"credit_card_accounts":[]},{"user_id":"11339564-8dfe-44b7-ab20-6409684cface","deposit_accounts":[],"savings_accounts":[{"account_id":"08016627-11ef-4ab8-b90b-9ad0a9af50ba","physical_cards":[],"virtual_cards":[],"top_up_operations":[],"purchase_operations":[],"transfer_operations":[],"cash_withdrawal_operations":[]}],"debit_card_accounts":[{"account_id":"e129204b-672b-49fd-97c8-a41bfecf2f04","physical_cards":[],"virtual_cards":[],"top_up_operations":[],"purchase_operations":[],"transfer_operations":[],"cash_withdrawal_operations":[]}],"credit_card_accounts":[]},{"user_id":"87a96921-e219-40d8-a20e-3266a6c27ff0","deposit_accounts":[],"savings_accounts":[{"account_id":"9a9baefa-999c-4fc1-b13f-face9c6c6ff4","physical_cards":[],"virtual_cards":[],"top_up_operations":[],"purchase_operations":[],"transfer_operations":[],"cash_withdrawal_operations":[]}],"debit_card_accounts":[{"account_id":"22a6a2fb-25df-4f9c-96e5-e8077641a924","physical_cards":[],"virtual_cards":[],"top_up_operations":[],"purchase_operations":[],"transfer_operations":[],"cash_withdrawal_operations":[]}],"credit_card_accounts":[]},{"user_id":"1cacca86-efb6-440e-bc0a-7cecb75e761d","deposit_accounts":[],"savings_accounts":[{"account_id":"392a45f8-ba68-4796-84eb-21b52fa328ea","physical_cards":[],"virtual_cards":[],"top_up_operations":[],"purchase_operations":[],"transfer_operations":[],"cash_withdrawal_operations":[]}],"debit_card_accounts":[{"account_id":"65285302-7955-4647-82d6-d68e70c921f1","physical_cards":[],"virtual_cards":[],"top_up_operations":[],"purchase_operations":[],"transfer_operations":[],"cash_withdrawal_operations":[]}],"credit_card_accounts":[]},{"user_id":"5ea653c4-25e8-4e5a-9199-35d1a640cbe0","deposit_accounts":[],"savings_accounts":[{"account_id":"70449b75-457a-437e-8d00-b6382f952c95","physical_cards":[],"virtual_cards":[],"top_up_operations":[],"purchase_operations":[],"transfer_operations":[],"cash_withdrawal_operations":[]}],"debit_card_accounts":[{"account_id":"6dd4dabd-29ca-493a-b1f4-2a41fa81cc4a","physical_cards":[],"virtual_cards":[],"top_up_operations":[],"purchase_operations":[],"transfer_operations":[],"cash_withdrawal_operations":[]}],"credit_card_accounts":[]},{"user_id":"f85f1cc2-80f4-4db1-8768-75ae1fbb51c5","deposit_accounts":[],"savings_accounts":[{"account_id":"1c8117ba-1083-4c16-a316-27906a1ab7ce","physical_cards":[],"virtual_cards":[],"top_up_operations":[],"purchase_operations":[],"transfer_operations":[],"cash_withdrawal_operations":[]}],"debit_card_accounts":[{"account_id":"2f554f2c-4e53-4659-a2cd-0223239b2bc1","physical_cards":[],"virtual_cards":[],"top_up_operations":[],"purchase_operations":[],"transfer_operations":[],"cash_withdrawal_operations":[]}],"credit_card_accounts":[]},{"user_id":"2f79ae39-2138-485f-bf1f-064e839a0dea","deposit_accounts":[],"savings_accounts":[{"account_id":"f72c221f-7575-4783-8c3b-932d6d94b473","physical_cards":[],"virtual_cards":[],"top_up_operations":[],"purchase_operations":[],"transfer_operations":[],"cash_withdrawal_operations":[]}],"debit_card_accounts":[{"account_id":"79b294cc-8dd8-459c-a004-3477de434377","physical_cards":[],"virtual_cards":[],"top_up_operations":[],"purchase_operations":[],"transfer_operations":[],"cash_withdrawal_operations":[]}],"credit_card_accounts":[]},{"user_id":"85bc46c0-7ea0-4617-b494-9a578ad21099","deposit_accounts":[],"savings_accounts":[{"account_id":"2a52e304-24c5-4bc0-aed5-6545901e86a4","physical_cards":[],"virtual_cards":[],"top_up_operations":[],"purchase_operations":[],"transfer_operations":[],"cash_withdrawal_operations":[]}],"debit_card_accounts":[{"account_id":"1a8f30f8-184a-4739-9aed-a6c28217c593","physical_cards":[],"virtual_cards":[],"top_up_operations":[],"purchase_operations":[],"transfer_operations":[],"cash_withdrawal_operations":[]}],"credit_card_accounts":[]},{"user_id":"67ce5c1f-a936-4272-9d7a-9bc4cd47b4b8","deposit_accounts":[],"savings_accounts":[{"account_id":"cb937f9c-e059-45b5-9e74-c19ecdd3d611","physical_cards":[],"virtual_cards":[],"top_up_operations":[],"purchase_operations":[],"transfer_operations":[],"cash_withdrawal_operations":[]}],"debit_card_accounts":[{"account_id":"9b2d7bc2-f1f6-463d-ba83-e12f746c509b","physical_cards":[],"virtual_cards":[],"top_up_operations":[],"purchase_operations":[],"transfer_operations":[],"cash_withdrawal_operations":[]}],"credit_card_accounts":[]},{"user_id":"c3700e74-4704-40be-8ca0-15e7f3796b05","deposit_accounts":[],"savings_accounts":[{"account_id":"f37e9138-9eb3-4200-8c79-8583cbfe4640","physical_cards":[],"virtual_cards":[],"top_up_operations":[],"purchase_operations":[],"transfer_operations":[],"cash_withdrawal_operations":[]}],"debit_card_accounts":[{"account_id":"27f2d161-dd84-4ac4-aeb1-d536631a932c","physical_cards":[],"virtual_cards":[],"top_up_operations":[],"purchase_operations":[],"transfer_operations":[],"cash_withdrawal_operations":[]}],"credit_card_accounts":[]},{"user_id":"a71f6793-dcab-47be-9cb7-e835a804a61f","deposit_accounts":[],"savings_accounts":[{"account_id":"a83c57e6-1b2f-4853-a63b-324121434090","physical_cards":[],"virtual_cards":[],"top_up_operations":[],"purchase_operations":[],"transfer_operations":[],"cash_withdrawal_operations":[]}],"debit_card_accounts":[{"account_id":"899f3646-f182-4fbf-8231-7884e8267967","physical_cards":[],"virtual_cards":[],"top_up_operations":[],"purchase_operations":[],"transfer_operations":[],"cash_withdrawal_operations":[]}],"credit_card_accounts":[]},{"user_id":"f1c49534-3215-4187-be7f-bdf267ed1e81","deposit_accounts":[],"savings_accounts":[{"account_id":"679a5b91-dd70-455a-8a9f-b53ac9f22491","physical_cards":[],"virtual_cards":[],"top_up_operations":[],"purchase_operations":[],"transfer_operations":[],"cash_withdrawal_operations":[]}],"debit_card_accounts":[{"account_id":"ed431e59-8dba-49d6-8029-fd1dfd1e52f8","physical_cards":[],"virtual_cards":[],"top_up_operations":[],"purchase_operations":[],"transfer_operations":[],"cash_withdrawal_operations":[]}],"credit_card_accounts":[]},{"user_id":"67a9cb83-1acc-4a56-9b10-f67a6e6a63ec","deposit_accounts":[],"savings_accounts":[{"account_id":"6318cf8b-c4d2-4bf2-bf18-b4c1142d1a8c","physical_cards":[],"virtual_cards":[],"top_up_operations":[],"purchase_operations":[],"transfer_operations":[],"cash_withdrawal_operations":[]}],"debit_card_accounts":[{"account_id":"c8165bb9-ec4e-4a8d-89c1-eaa4f1d24b85","physical_cards":[],"virtual_cards":[],"top_up_operations":[],"purchase_operations":[],"transfer_operations":[],"cash_withdrawal_operations":[]}],"credit_card_accounts":[]},{"user_id":"9ac54a19-305e-499f-808c-88cb178a86d9","deposit_accounts":[],"savings_accounts":[{"account_id":"8a8135cf-d262-4857-9284-5be4e3b4f40d","physical_cards":[],"virtual_cards":[],"top_up_operations":[],"purchase_operations":[],"transfer_operations":[],"cash_withdrawal_operations":[]}],"debit_card_accounts":[{"account_id":"993bb37e-dfd8-48a3-aecf-adca58f4fe92","physical_cards":[],"virtual_cards":[],"top_up_operations":[],"purchase_operations":[],"transfer_operations":[],"cash_withdrawal_operations":[]}],"credit_card_accounts":[]},{"user_id":"104661b5-8d80-4056-90e3-8ccf5f08283b","deposit_accounts":[],"savings_accounts":[{"account_id":"059084ab-1783-4ff8-8a46-7fe7fed1d7f7","physical_cards":[],"virtual_cards":[],"top_up_operations":[],"purchase_operations":[],"transfer_operations":[],"cash_withdrawal_operations":[]}],"debit_card_accounts":[{"account_id":"4f57bf25-1571-400b-a33e-572e03c41746","physical_cards":[],"virtual_cards":[],"top_up_operations":[],"purchase_operations":[],"transfer_operations":[],"cash_withdrawal_operations":[]}],"credit_card_accounts":[]},{"user_id":"864f82a8-de2f-4bcc-9e41-8439147dbcb8","deposit_accounts":[],"savings_accounts":[{"account_id":"fbce1a93-513e-431d-8678-4526c8300eae","physical_cards":[],"virtual_cards":[],"top_up_operations":[],"purchase_operations":[],"transfer_operations":[],"cash_withdrawal_operations":[]}],"debit_card_accounts":[{"account_id":"31a071e2-427c-4306-939c-92937fbe160c","physical_cards":[],"virtual_cards":[],"top_up_operations":[],"purchase_operations":[],"transfer_operations":[],"cash_withdrawal_operations":[]}],"credit_card_accounts":[]},{"user_id":"099c7648-1cad-4c6a-bdd3-4ccf923b3141","deposit_accounts":[],"savings_accounts":[{"account_id":"1f8c2f3e-ecde-4426-9f49-9c13faaeafa2","physical_cards":[],"virtual_cards":[],"top_up_operations":[],"purchase_operations":[],"transfer_operations":[],"cash_withdrawal_operations":[]}],"debit_card_accounts":[{"account_id":"1aeabd03-c584-4169-8f02-1564b32e630a","physical_cards":[],"virtual_cards":[],"top_up_operations":[],"purchase_operations":[],"transfer_operations":[],"cash_withdrawal_operations":[]}],"credit_card_accounts":[]},{"user_id":"4c749529-8149-43f5-b732-15ab5e1199ac","deposit_accounts":[],"savings_accounts":[{"account_id":"bc67b506-e88f-47a3-b936-0581e1aa7930","physical_cards":[],"virtual_cards":[],"top_up_operations":[],"purchase_operations":[],"transfer_operations":[],"cash_withdrawal_operations":[]}],"debit_card_accounts":[{"account_id":"deded2a5-c01c-4bbd-9bba-2974631a8df8","physical_cards":[],"virtual_cards":[],"top_up_operations":[],"purchase_operations":[],"transfer_operations":[],"cash_withdrawal_operations":[]}],"credit_card_accounts":[]},{"user_id":"80ca2064-36fb-48a8-8f5b-312d11de14f3","deposit_accounts":[],"savings_accounts":[{"account_id":"3d97d3b4-16da-4ec6-86c5-57cc05c2c568","physical_cards":[],"virtual_cards":[],"top_up_operations":[],"purchase_operations":[],"transfer_operations":[],"cash_withdrawal_operations":[]}],"debit_card_accounts":[{"account_id":"26e6884f-dd14-4953-b940-3dcd2a4a1059","physical_cards":[],"virtual_cards":[],"top_up_operations":[],"purchase_operations":[],"transfer_operations":[],"cash_withdrawal_operations":[]}],"credit_card_accounts":[]},{"user_id":"6bd39b01-eb00-40b4-a3b4-d1b8b5f25374","deposit_accounts":[],"savings_accounts":[{"account_id":"919da169-bc92-48ea-9a70-5a64ee1768a8","physical_cards":[],"virtual_cards":[],"top_up_operations":[],"purchase_operations":[],"transfer_operations":[],"cash_withdrawal_operations":[]}],"debit_card_accounts":[{"account_id":"b0bd1f55-1e15-4aa5-abc6-3d0ebe9674f0","physical_cards":[],"virtual_cards":[],"top_up_operations":[],"purchase_operations":[],"transfer_operations":[],"cash_withdrawal_operations":[]}],"credit_card_accounts":[]},{"user_id":"da580e04-718f-4ac1-aa0e-0730a9316daf","deposit_accounts":[],"savings_accounts":[{"account_id":"f5205f2e-c381-4930-918f-39f941a55097","physical_cards":[],"virtual_cards":[],"top_up_operations":[],"purchase_operations":[],"transfer_operations":[],"cash_withdrawal_operations":[]}],"debit_card_accounts":[{"account_id":"32f4e522-0ff2-4b02-821c-adb56d701ad9","physical_cards":[],"virtual_cards":[],"top_up_operations":[],"purchase_operations":[],"transfer_operations":[],"cash_withdrawal_operations":[]}],"credit_card_accounts":[]},{"user_id":"1fc9bbe3-4f79-45bf-bf99-4450ce91b4db","deposit_accounts":[],"savings_accounts":[{"account_id":"7f64b5bf-6d76-4f6f-ba7f-33ecf50f4ae6","physical_cards":[],"virtual_cards":[],"top_up_operations":[],"purchase_operations":[],"transfer_operations":[],"cash_withdrawal_operations":[]}],"debit_card_accounts":[{"account_id":"9577e6a6-d7a3-45ea-9620-57c38b2303ff","physical_cards":[],"virtual_cards":[],"top_up_operations":[],"purchase_operations":[],"transfer_operations":[],"cash_withdrawal_operations":[]}],"credit_card_accounts":[]},{"user_id":"017b7151-36db-4210-a7ac-2a7917b8aa27","deposit_accounts":[],"savings_accounts":[{"account_id":"b019a188-d8d2-42e0-93d5-10d71471677b","physical_cards":[],"virtual_cards":[],"top_up_operations":[],"purchase_operations":[],"transfer_operations":[],"cash_withdrawal_operations":[]}],"debit_card_accounts":[{"account_id":"420b6f2b-144b-42f1-b318-d61b6c5982c6","physical_cards":[],"virtual_cards":[],"top_up_operations":[],"purchase_operations":[],"transfer_operations":[],"cash_withdrawal_operations":[]}],"credit_card_accounts":[]},{"user_id":"44af2c8b-8949-44ae-8973-3f3d5ae11ed2","deposit_accounts":[],"savings_accounts":[{"account_id":"0749dd2a-172f-44dd-ae22-4635c6208e1c","physical_cards":[],"virtual_cards":[],"top_up_operations":[],"purchase_operations":[],"transfer_operations":[],"cash_withdrawal_operations":[]}],"debit_card_accounts":[{"account_id":"2cd177a6-7b02-4edd-bbd0-0a0bcfa67a24","physical_cards":[],"virtual_cards":[],"top_up_operations":[],"purchase_operations":[],"transfer_operations":[],"cash_withdrawal_operations":[]}],"credit_card_accounts":[]},{"user_id":"616ce0b9-4d5a-47e7-a845-fdf955e947a8","deposit_accounts":[],"savings_accounts":[{"account_id":"8646daff-5d37-465e-a2c6-9d29e95da200","physical_cards":[],"virtual_cards":[],"top_up_operations":[],"purchase_operations":[],"transfer_operations":[],"cash_withdrawal_operations":[]}],"debit_card_accounts":[{"account_id":"a37ecab7-03da-4c24-8a21-02467b6bc0ce","physical_cards":[],"virtual_cards":[],"top_up_operations":[],"purchase_operations":[],"transfer_operations":[],"cash_withdrawal_operations":[]}],"credit_card_accounts":[]},{"user_id":"d7da5bc3-3809-43b4-85bb-376878e27e4f","deposit_accounts":[],"savings_accounts":[{"account_id":"5288b7b8-9fca-4562-85a0-358aabcc764d","physical_cards":[],"virtual_cards":[],"top_up_operations":[],"purchase_operations":[],"transfer_operations":[],"cash_withdrawal_operations":[]}],"debit_card_accounts":[{"account_id":"0214a251-b94d-4d28-80c7-35d22331afda","physical_cards":[],"virtual_cards":[],"top_up_operations":[],"purchase_operations":[],"transfer_operations":[],"cash_withdrawal_operations":[]}],"credit_card_accounts":[]},{"user_id":"e1350d38-6fbb-4a9d-a5f3-fbf4088e14fd","deposit_accounts":[],"savings_accounts":[{"account_id":"b5b9268f-f969-4d06-a01e-6264ea7a94be","physical_cards":[],"virtual_cards":[],"top_up_operations":[],"purchase_operations":[],"transfer_operations":[],"cash_withdrawal_operations":[]}],"debit_card_accounts":[{"account_id":"9a7237ed-220d-42fd-929b-e6eb0ac8ead2","physical_cards":[],"virtual_cards":[],"top_up_operations":[],"purchase_operations":[],"transfer_operations":[],"cash_withdrawal_operations":[]}],"credit_card_accounts":[]},{"user_id":"75f1085d-133b-4f7a-997d-7c42459f3a55","deposit_accounts":[],"savings_accounts":[{"account_id":"17aa1977-27fd-405e-92ae-33a823f7454a","physical_cards":[],"virtual_cards":[],"top_up_operations":[],"purchase_operations":[],"transfer_operations":[],"cash_withdrawal_operations":[]}],"debit_card_accounts":[{"account_id":"ed65fad4-6b5f-43fd-9607-505e4af5c2ea","physical_cards":[],"virtual_cards":[],"top_up_operations":[],"purchase_operations":[],"transfer_operations":[],"cash_withdrawal_operations":[]}],"credit_card_accounts":[]},{"user_id":"fe8d30e0-a3fb-496e-ac91-72a7a4ea5b84","deposit_accounts":[],"savings_accounts":[{"account_id":"c4859158-b94d-4649-bf4f-4792ed5b217b","physical_cards":[],"virtual_cards":[],"top_up_operations":[],"purchase_operations":[],"transfer_operations":[],"cash_withdrawal_operations":[]}],"debit_card_accounts":[{"account_id":"1db30e6b-0dba-422b-bb17-92fabfab3851","physical_cards":[],"virtual_cards":[],"top_up_operations":[],"purchase_operations":[],"transfer_operations":[],"cash_withdrawal_operations":[]}],"credit_card_accounts":[]},{"user_id":"4ffdd2e7-53cb-446e-971c-8d30e38d58d5","deposit_accounts":[],"savings_accounts":[{"account_id":"ec41a89c-493b-4028-98ac-8b6ea2bb59bc","physical_cards":[],"virtual_cards":[],"top_up_operations":[],"purchase_operations":[],"transfer_operations":[],"cash_withdrawal_operations":[]}],"debit_card_accounts":[{"account_id":"7d72b230-85ff-4366-9b2b-7663507fe96a","physical_cards":[],"virtual_cards":[],"top_up_operations":[],"purchase_operations":[],"transfer_operations":[],"cash_withdrawal_operations":[]}],"credit_card_accounts":[]},{"user_id":"333a0652-2031-4402-b59d-95ff8019069e","deposit_accounts":[],"savings_accounts":[{"account_id":"792365fd-61bf-4293-ae07-f6c3eaa9659c","physical_cards":[],"virtual_cards":[],"top_up_operations":[],"purchase_operations":[],"transfer_operations":[],"cash_withdrawal_operations":[]}],"debit_card_accounts":[{"account_id":"421fae66-b4cf-460b-ba90-3141c4c0b627","physical_cards":[],"virtual_cards":[],"top_up_operations":[],"purchase_operations":[],"transfer_operations":[],"cash_withdrawal_operations":[]}],"credit_card_accounts":[]},{"user_id":"ac6f8fb1-671d-4738-b55f-349f1db5013b","deposit_accounts":[],"savings_accounts":[{"account_id":"1567bb6a-b862-4834-96fe-a146b8db554f","physical_cards":[],"virtual_cards":[],"top_up_operations":[],"purchase_operations":[],"transfer_operations":[],"cash_withdrawal_operations":[]}],"debit_card_accounts":[{"account_id":"02b604c5-ac46-4c06-a3f6-7c338e57bb7c","physical_cards":[],"virtual_cards":[],"top_up_operations":[],"purchase_operations":[],"transfer_operations":[],"cash_withdrawal_operations":[]}],"credit_card_accounts":[]},{"user_id":"68c8e4a9-4fa8-4a4d-9bb5-fc918520c6fe","deposit_accounts":[],"savings_accounts":[{"account_id":"4e770d5b-9a1a-4be7-ad60-cb92a11ee007","physical_cards":[],"virtual_cards":[],"top_up_operations":[],"purchase_operations":[],"transfer_operations":[],"cash_withdrawal_operations":[]}],"debit_card_accounts":[{"account_id":"52a3543f-4a2e-47f7-a2c3-9273f22afde7","physical_cards":[],"virtual_cards":[],"top_up_operations":[],"purchase_operations":[],"transfer_operations":[],"cash_withdrawal_operations":[]}],"credit_card_accounts":[]},{"user_id":"8a364b80-2bb9-464c-8d91-264aa02d00fd","deposit_accounts":[],"savings_accounts":[{"account_id":"fdea2493-9169-40d5-a289-46b8cee2014a","physical_cards":[],"virtual_cards":[],"top_up_operations":[],"purchase_operations":[],"transfer_operations":[],"cash_withdrawal_operations":[]}],"debit_card_accounts":[{"account_id":"249795d8-54e2-465d-9fc9-a7042e2f86fe","physical_cards":[],"virtual_cards":[],"top_up_operations":[],"purchase_operations":[],"transfer_operations":[],"cash_withdrawal_operations":[]}],"credit_card_accounts":[]},{"user_id":"33f9caed-0d17-4fb4-9384-38acf230878b","deposit_accounts":[],"savings_accounts":[{"account_id":"a13099f3-e462-4cd3-a4b4-06e5642c419b","physical_cards":[],"virtual_cards":[],"top_up_operations":[],"purchase_operations":[],"transfer_operations":[],"cash_withdrawal_operations":[]}],"debit_card_accounts":[{"account_id":"8e8ff78a-fd04-48b8-a558-9a336c0d7f1a","physical_cards":[],"virtual_cards":[],"top_up_operations":[],"purchase_operations":[],"transfer_operations":[],"cash_withdrawal_operations":[]}],"credit_card_accounts":[]},{"user_id":"b9946ef8-8e32-4268-a796-af082bbcb5ba","deposit_accounts":[],"savings_accounts":[{"account_id":"1be79541-c236-4a55-a215-faa5e6855944","physical_cards":[],"virtual_cards":[],"top_up_operations":[],"purchase_operations":[],"transfer_operations":[],"cash_withdrawal_operations":[]}],"debit_card_accounts":[{"account_id":"58c854eb-0fcd-49b5-82f6-996dbafb6381","physical_cards":[],"virtual_cards":[],"top_up_operations":[],"purchase_operations":[],"transfer_operations":[],"cash_withdrawal_operations":[]}],"credit_card_accounts":[]},{"user_id":"365bfd01-90ce-461f-8cb0-cec07462e7eb","deposit_accounts":[],"savings_accounts":[{"account_id":"bb707ec4-777f-45e8-8a95-71c578370733","physical_cards":[],"virtual_cards":[],"top_up_operations":[],"purchase_operations":[],"transfer_operations":[],"cash_withdrawal_operations":[]}],"debit_card_accounts":[{"account_id":"126c0fe4-2857-4828-9bd3-2072478c1c7c","physical_cards":[],"virtual_cards":[],"top_up_operations":[],"purchase_operations":[],"transfer_operations":[],"cash_withdrawal_operations":[]}],"credit_card_accounts":[]},{"user_id":"8f3039d9-25e2-4ea2-85ca-6d68ce08a543","deposit_accounts":[],"savings_accounts":[{"account_id":"764a0581-8398-4179-9415-ec478afd65fc","physical_cards":[],"virtual_cards":[],"top_up_operations":[],"purchase_operations":[],"transfer_operations":[],"cash_withdrawal_operations":[]}],"debit_card_accounts":[{"account_id":"1d0301f7-9b70-4420-b120-217f8fd7840a","physical_cards":[],"virtual_cards":[],"top_up_operations":[],"purchase_operations":[],"transfer_operations":[],"cash_withdrawal_operations":[]}],"credit_card_accounts":[]},{"user_id":"6f24b61f-08af-48eb-b4c7-9d57508d1187","deposit_accounts":[],"savings_accounts":[{"account_id":"32ab9349-4cd8-4d52-9e37-675714619179","physical_cards":[],"virtual_cards":[],"top_up_operations":[],"purchase_operations":[],"transfer_operations":[],"cash_withdrawal_operations":[]}],"debit_card_accounts":[{"account_id":"a513ef4e-6c3f-43e6-8f37-66255a792fe7","physical_cards":[],"virtual_cards":[],"top_up_operations":[],"purchase_operations":[],"transfer_operations":[],"cash_withdrawal_operations":[]}],"credit_card_accounts":[]},{"user_id":"cb2031b6-9f73-440b-ae95-2422bb9eeeac","deposit_accounts":[],"savings_accounts":[{"account_id":"829df17d-9730-43e4-b66e-665780e96379","physical_cards":[],"virtual_cards":[],"top_up_operations":[],"purchase_operations":[],"transfer_operations":[],"cash_withdrawal_operations":[]}],"debit_card_accounts":[{"account_id":"8d061eb9-749a-46a8-b530-6dc661f7f5de","physical_cards":[],"virtual_cards":[],"top_up_operations":[],"purchase_operations":[],"transfer_operations":[],"cash_withdrawal_operations":[]}],"credit_card_accounts":[]}]}